./.gitignore
./LICENSE
./PKG-INFO
./README.md
./pyproject.toml
./uv.lock
./django_genc/__init__.py
./django_genc/admin.py
./django_genc/apps.py
./django_genc/models.py
./django_genc/urls.py
./django_genc/data/genc_iso_combined.csv
./django_genc/migrations/0001_initial.py
./django_genc/migrations/0002_alter_countrycode_id.py
./django_genc/migrations/__init__.py
./tests/__init__.py
./tests/conftest.py
./tests/test_admin.py
./tests/test_migrations.py
./tests/test_models.py
django_genc-0.1.2.dist-info/METADATA
django_genc-0.1.2.dist-info/WHEEL
django_genc-0.1.2.dist-info/licenses/LICENSE
django_genc-0.1.2.dist-info/RECORD
