Metadata-Version: 2.4
Name: django-genc
Version: 0.1.2
Summary: A django app for working with GENC country codes
Project-URL: Homepage, https://github.com/makegov/django-genc
Project-URL: Documentation, https://django-genc.readthedocs.io/
Project-URL: Repository, https://github.com/makegov/django-genc
Project-URL: Issues, https://github.com/makegov/django-genc/issues
Author-email: "V. David Zvenyach" <dave@makegov.com>
License-Expression: Apache-2.0
License-File: LICENSE
Keywords: codes,country,django,genc,iso
Classifier: Development Status :: 4 - Beta
Classifier: Framework :: Django
Classifier: Framework :: Django :: 4.0
Classifier: Framework :: Django :: 4.1
Classifier: Intended Audience :: Developers
Classifier: License :: OSI Approved :: Apache Software License
Classifier: Operating System :: OS Independent
Classifier: Programming Language :: Python
Classifier: Programming Language :: Python :: 3.11
Classifier: Topic :: Software Development :: Libraries :: Python Modules
Requires-Python: >=3.11
Requires-Dist: django>=4.0
Provides-Extra: dev
Requires-Dist: black; extra == 'dev'
Requires-Dist: coverage; extra == 'dev'
Requires-Dist: flake8; extra == 'dev'
Requires-Dist: isort; extra == 'dev'
Requires-Dist: pytest; extra == 'dev'
Requires-Dist: pytest-django; extra == 'dev'
Provides-Extra: docs
Requires-Dist: sphinx; extra == 'docs'
Requires-Dist: sphinx-rtd-theme; extra == 'docs'
